README.txt
setup.py
collective/__init__.py
collective.portlet.similarcontent.egg-info/PKG-INFO
collective.portlet.similarcontent.egg-info/SOURCES.txt
collective.portlet.similarcontent.egg-info/dependency_links.txt
collective.portlet.similarcontent.egg-info/entry_points.txt
collective.portlet.similarcontent.egg-info/namespace_packages.txt
collective.portlet.similarcontent.egg-info/not-zip-safe
collective.portlet.similarcontent.egg-info/requires.txt
collective.portlet.similarcontent.egg-info/top_level.txt
collective/portlet/__init__.py
collective/portlet/similarcontent/__init__.py
collective/portlet/similarcontent/configure.zcml
collective/portlet/similarcontent/similarcontentportlet.pt
collective/portlet/similarcontent/similarcontentportlet.py
collective/portlet/similarcontent/version.txt
collective/portlet/similarcontent/profiles/default/metadata.xml
collective/portlet/similarcontent/profiles/default/portlets.xml
collective/portlet/similarcontent/tests/__init__.py
collective/portlet/similarcontent/tests/base.py
collective/portlet/similarcontent/tests/test_portlet.py
docs/HISTORY.txt
docs/INSTALL.txt
docs/LICENSE.GPL
docs/LICENSE.txt