Metadata-Version: 1.0
Name: collective.portlet.similarcontent
Version: 1.5
Summary: A Plone portlet that uses the catalog internals to find 'similar' content to the page you are looking at
Home-page: http://plone.org
Author: Matt Hamilton
Author-email: matth@netsight.co.uk
License: ZPL 2.1
Keywords: plone portlet similar related
Platform: UNKNOWN
Classifier: Framework :: Plone
Classifier: Programming Language :: Python
